easy_spreadsheet/__init__.py
tests/__init__.py
tests/test_default.py
easy_spreadsheet-1.3.16.dist-info/LICENSE
easy_spreadsheet-1.3.16.dist-info/METADATA
easy_spreadsheet-1.3.16.dist-info/WHEEL
easy_spreadsheet-1.3.16.dist-info/top_level.txt
easy_spreadsheet-1.3.16.dist-info/RECORD
