Metadata-Version: 2.1
Name: easy-spreadsheet
Version: 1.3.16
Summary: Easy use Google Spreadsheet in Python.
Home-page: https://github.com/da-huin/easy_spreadsheet
Author: JunYeong Park
Author-email: dahuin000@gmail.com
License: MIT
Download-URL: https://github.com/da-huin/easy_spreadsheet/archive/master.zip
Platform: UNKNOWN
Classifier: Programming Language :: Python :: 3
Requires-Dist: boto3
Requires-Dist: pandas
Requires-Dist: gspread
Requires-Dist: oauth2client
